CQG_lib-0.0.4.dist-info/METADATA
CQG_lib-0.0.4.dist-info/RECORD
CQG_lib-0.0.4.dist-info/WHEEL
CQG_lib-0.0.4.dist-info/top_level.txt
cqg_lib/__init__.py
