Metadata-Version: 2.1
Name: CQG-lib
Version: 0.0.4
Summary: A package to chart in CQG Integrated Client
Home-page: https://git.denver.cqg/ninal/Boundfit.PythonNet
Author: Nina Lin
Author-email: ninal@cqg.com
License: UNKNOWN
Platform: UNKNOWN
Classifier: Programming Language :: Python :: 3
Classifier: License :: OSI Approved :: MIT License
Classifier: Operating System :: OS Independent
